[
  {
    "NAMES": ["盛放形态"],
    "DESCRIPTION": "获得 #b%d 点力量。"
  },
  {
    "NAMES": ["凋零形态"],
    "DESCRIPTION": "获得 #b%d 点敏捷。"
  },
  {
    "NAMES": ["椿花养料"],
    "DESCRIPTION": "每当有敌人死亡时，获得 #b%d 点护甲和 #b%d 点敏捷。"
  },
  {
    "NAMES": ["吹又生"],
    "DESCRIPTION": "每回合第一次受到伤害时，回复 #b%d 点生命值并获得 #b%d 点力量。"
  },
  {
    "NAMES": ["休养生息"],
    "DESCRIPTION": "在你的回合结束时，回复 #b%d 点生命值并获得 #b%d 点力量。"
  },
  {
    "NAMES": ["沃土"],
    "DESCRIPTION": "每当有一张牌被消耗时，抽 #b%d 张牌。"
  },
  {
    "NAMES": ["注毒"],
    "DESCRIPTION": "每回合开始时，失去 #b%d 点生命值，然后减少 #b1 层注毒。"
  }
]